trapga/trapga.py
trapga/utils.py
trapga-1.0.1.dist-info/METADATA
trapga-1.0.1.dist-info/WHEEL
trapga-1.0.1.dist-info/entry_points.txt
trapga-1.0.1.dist-info/top_level.txt
trapga-1.0.1.dist-info/RECORD
